[
  {
    "mmsi": "111219501",
    "recordTime": [
      1500895555,
      1500897076,
      1500899133,
      1500900954,
      1500983753,
      1500985555,
      1500986430,
      1501062954,
      1501063930,
      1501065464,
      1501233956,
      1501235486,
      1501332956,
      1501335938,
      1501435512,
      1501437528,
      1501505729,
      1501507549,
      1501509761,
      1501638394,
      1501639981,
      1501642310,
      1501666431,
      1501669371,
      1501865741,
      1501868801,
      1501968355,
      1501970155,
      1501972378,
      1502002556,
      1502003578,
      1502011293,
      1502014563,
      1502108685,
      1502110113,
      1502136920,
      1502142900,
      1502152230,
      1502196919,
      1502198624,
      1502372812,
      1502429156,
      1502432757,
      1502434556,
      1502435249,
      1502440047,
      1502612728,
      1502614206,
      1502621699,
      1502961958,
      1503051770,
      1503063601,
      1503069110,
      1503153842
    ],
    "geoJSON": {
      "type": "LineString",
      "coordinates": [
        [
          9.73625,
          57.08433
        ],
        [
          9.72338,
          57.57291
        ],
        [
          10.16127,
          57.61311
        ],
        [
          9.66787,
          57.12751
        ],
        [
          9.80101,
          57.48829
        ],
        [
          10.08575,
          57.40408
        ],
        [
          9.27787,
          56.98795
        ],
        [
          9.86594,
          57.06813
        ],
        [
          9.23169,
          57.10074
        ],
        [
          9.06182,
          56.34428
        ],
        [
          10.28283,
          55.13773
        ],
        [
          9.41812,
          55.207
        ],
        [
          12.05533,
          56.07341
        ],
        [
          10.00562,
          55.33388
        ],
        [
          9.72013,
          55.50808
        ],
        [
          9.44449,
          55.32471
        ],
        [
          10.33945,
          55.59608
        ],
        [
          10.38375,
          55.41901
        ],
        [
          9.66006,
          55.27473
        ],
        [
          10.29971,
          55.05787
        ],
        [
          10.35111,
          55.3471
        ],
        [
          9.3954,
          55.23499
        ],
        [
          10.26562,
          54.89766
        ],
        [
          9.51728,
          55.15377
        ],
        [
          10.31816,
          55.02099
        ],
        [
          9.54164,
          55.16003
        ],
        [
          10.97535,
          55.16112
        ],
        [
          10.88123,
          54.87951
        ],
        [
          9.51621,
          55.19348
        ],
        [
          9.51839,
          54.91622
        ],
        [
          9.56348,
          55.19303
        ],
        [
          10.80231,
          54.86812
        ],
        [
          9.54838,
          55.17693
        ],
        [
          10.33335,
          55.56523
        ],
        [
          9.75559,
          55.24233
        ],
        [
          9.32346,
          55.21206
        ],
        [
          6.83598,
          55.8506
        ],
        [
          9.28451,
          55.22133
        ],
        [
          10.44708,
          55.76908
        ],
        [
          10.35233,
          55.3935
        ],
        [
          8.4433,
          55.16275
        ],
        [
          12.45003,
          55.51763
        ],
        [
          12.69354,
          55.95121
        ],
        [
          12.70706,
          55.72918
        ],
        [
          12.12213,
          55.59055
        ],
        [
          9.43866,
          55.23722
        ],
        [
          9.06767,
          56.31843
        ],
        [
          9.83854,
          57.10249
        ],
        [
          9.12674,
          56.32056
        ],
        [
          11.71211,
          55.61293
        ],
        [
          12.61544,
          55.67342
        ],
        [
          11.38715,
          55.37909
        ],
        [
          10.25254,
          56.14899
        ],
        [
          12.12101,
          55.59102
        ]
      ]
    }
  }
]